.venv/Lib/site-packages/_virtualenv.py
.venv/Lib/site-packages/six.py
.venv/Lib/site-packages/xmltodict.py
.venv/Lib/site-packages/zipp.py
.venv/Lib/site-packages/_distutils_hack/__init__.py
.venv/Lib/site-packages/_distutils_hack/override.py
.venv/Lib/site-packages/bleach/__init__.py
.venv/Lib/site-packages/bleach/callbacks.py
.venv/Lib/site-packages/bleach/css_sanitizer.py
.venv/Lib/site-packages/bleach/html5lib_shim.py
.venv/Lib/site-packages/bleach/linkifier.py
.venv/Lib/site-packages/bleach/parse_shim.py
.venv/Lib/site-packages/bleach/sanitizer.py
.venv/Lib/site-packages/bleach/_vendor/__init__.py
.venv/Lib/site-packages/bleach/_vendor/parse.py
.venv/Lib/site-packages/bleach/_vendor/html5lib/__init__.py
.venv/Lib/site-packages/bleach/_vendor/html5lib/_ihatexml.py
.venv/Lib/site-packages/bleach/_vendor/html5lib/_inputstream.py
.venv/Lib/site-packages/bleach/_vendor/html5lib/_tokenizer.py
.venv/Lib/site-packages/bleach/_vendor/html5lib/_utils.py
.venv/Lib/site-packages/bleach/_vendor/html5lib/constants.py
.venv/Lib/site-packages/bleach/_vendor/html5lib/html5parser.py
.venv/Lib/site-packages/bleach/_vendor/html5lib/serializer.py
.venv/Lib/site-packages/bleach/_vendor/html5lib/_trie/__init__.py
.venv/Lib/site-packages/bleach/_vendor/html5lib/_trie/_base.py
.venv/Lib/site-packages/bleach/_vendor/html5lib/_trie/py.py
.venv/Lib/site-packages/bleach/_vendor/html5lib/filters/__init__.py
.venv/Lib/site-packages/bleach/_vendor/html5lib/filters/alphabeticalattributes.py
.venv/Lib/site-packages/bleach/_vendor/html5lib/filters/base.py
.venv/Lib/site-packages/bleach/_vendor/html5lib/filters/inject_meta_charset.py
.venv/Lib/site-packages/bleach/_vendor/html5lib/filters/lint.py
.venv/Lib/site-packages/bleach/_vendor/html5lib/filters/optionaltags.py
.venv/Lib/site-packages/bleach/_vendor/html5lib/filters/sanitizer.py
.venv/Lib/site-packages/bleach/_vendor/html5lib/filters/whitespace.py
.venv/Lib/site-packages/bleach/_vendor/html5lib/treeadapters/__init__.py
autoexportreader-0.0.2.dist-info/METADATA
autoexportreader-0.0.2.dist-info/WHEEL
autoexportreader-0.0.2.dist-info/licenses/License
autoexportreader-0.0.2.dist-info/RECORD
