Metadata-Version: 2.1
Name: autoexportreader
Version: 0.0.2
Summary: Koh Young 3D SPI autoexport file parser
Project-URL: Homepage, https://gitlab.com/blue-sleeves/autoexportreader
Project-URL: Bug Tracker, https://gitlab.com/blue-sleeves/autoexportreader/-/issues
Author-email: BlueSleeves <Lauri.Maertin@gmail.com>
License: Copyright 2022 Blue Sleeves
Classifier: License :: OSI Approved :: MIT License
Classifier: Operating System :: OS Independent
Classifier: Programming Language :: Python :: 3
Requires-Python: >=3.7
Requires-Dist: xmltodict~=0.13.0
